aiida_zeopp/__init__.py
aiida_zeopp/calculations/__init__.py
aiida_zeopp/calculations/network.py
aiida_zeopp/calculations/test_network.py
aiida_zeopp/data/__init__.py
aiida_zeopp/data/parameters.py
aiida_zeopp/data/test_parameters.py
aiida_zeopp/parsers/__init__.py
aiida_zeopp/parsers/network.py
aiida_zeopp/parsers/plain.py
aiida_zeopp/parsers/structure.py
aiida_zeopp/parsers/test_network.py
aiida_zeopp/parsers/test_plain.py
aiida_zeopp/parsers/test_structure.py
aiida_zeopp/tests/HKUST-1.block
aiida_zeopp/tests/HKUST-1.cif
aiida_zeopp/tests/HKUST-1.cssr
aiida_zeopp/tests/HKUST-1.sa
aiida_zeopp/tests/HKUST-1.volpo
aiida_zeopp/tests/MgO.cif
aiida_zeopp/tests/MgO.cssr
aiida_zeopp/tests/MgO.rad
aiida_zeopp/tests/P8bal_P1.chan
aiida_zeopp/tests/__init__.py
aiida_zeopp/tests/test_helpers.py
aiida_zeopp-2.0.0.dist-info/entry_points.txt
aiida_zeopp-2.0.0.dist-info/LICENSE
aiida_zeopp-2.0.0.dist-info/WHEEL
aiida_zeopp-2.0.0.dist-info/METADATA
aiida_zeopp-2.0.0.dist-info/RECORD
