Metadata-Version: 2.1
Name: aiida-zeopp
Version: 2.0.0
Summary: AiiDA plugin for zeo++
Keywords: aiida,workflows
Author-email: Leopold Talirz <leopold.talirz@epfl.ch>, Miriam Pougin <miriam.pougin@epfl.ch>
Requires-Python: >=3.8
Classifier: Development Status :: 5 - Production/Stable
Classifier: Framework :: AiiDA
Classifier: License :: OSI Approved :: MIT License
Classifier: Programming Language :: Python
Classifier: Programming Language :: Python :: 3.8
Classifier: Programming Language :: Python :: 3.9
Classifier: Programming Language :: Python :: 3.10
Classifier: Programming Language :: Python :: 3.11
Requires-Dist: aiida_core[atomic_tools]~=2.3
Requires-Dist: importlib_resources
Requires-Dist: voluptuous
Requires-Dist: aiida-zeopp[tests,pre-commit] ; extra == "dev"
Requires-Dist: pre-commit~=3.3 ; extra == "pre-commit"
Requires-Dist: black~=23.7 ; extra == "pre-commit"
Requires-Dist: isort~=5.12 ; extra == "pre-commit"
Requires-Dist: pylint~=2.17 ; extra == "pre-commit"
Requires-Dist: pgtest~=1.3,>=1.3.1 ; extra == "tests"
Requires-Dist: pytest~=6.0 ; extra == "tests"
Project-URL: Home, https://github.com/ltalirz/aiida-zeopp
Provides-Extra: dev
Provides-Extra: pre-commit
Provides-Extra: tests
